pyblaze/BlazeClient.py
pyblaze/__init__.py
pyblaze/enums.py
pyblaze/games/Crash.py
pyblaze/games/Double.py
pyblaze/games/GameClient.py
pyblaze/games/__init__.py
pyblaze/mixins/Hashable.py
pyblaze/mixins/__init__.py
pyblaze/models/User.py
pyblaze/models/__init__.py
pyblaze/models/base/Bet.py
pyblaze/models/base/CurrentResponse.py
pyblaze/models/base/__init__.py
pyblaze/models/blaze/Announcement.py
pyblaze/models/blaze/ChatRoomConfig.py
pyblaze/models/blaze/ChatRoomMessage.py
pyblaze/models/blaze/ChatRoomMessageUser.py
pyblaze/models/blaze/ChatRoomResponse.py
pyblaze/models/blaze/ChatRoomsResponse.py
pyblaze/models/blaze/Country.py
pyblaze/models/blaze/Currencies.py
pyblaze/models/blaze/Currency.py
pyblaze/models/blaze/Settings.py
pyblaze/models/blaze/Time.py
pyblaze/models/blaze/Version.py
pyblaze/models/blaze/__init__.py
pyblaze/models/crash/Bet.py
pyblaze/models/crash/CurrentResponse.py
pyblaze/models/crash/GetGameByIdResponse.py
pyblaze/models/crash/RecentHistoryResponse.py
pyblaze/models/crash/RecentsEntity.py
pyblaze/models/crash/RecentsResponse.py
pyblaze/models/crash/Record.py
pyblaze/models/crash/Result.py
pyblaze/models/crash/__init__.py
pyblaze/models/double/Bet.py
pyblaze/models/double/CurrentResponse.py
pyblaze/models/double/GetGameByIdResponse.py
pyblaze/models/double/RecentHistoryResponse.py
pyblaze/models/double/RecentsEntity.py
pyblaze/models/double/RecentsResponse.py
pyblaze/models/double/Record.py
pyblaze/models/double/Result.py
pyblaze/models/double/__init__.py
bonsancon_pyblaze-0.0.11.dist-info/LICENSE
bonsancon_pyblaze-0.0.11.dist-info/METADATA
bonsancon_pyblaze-0.0.11.dist-info/WHEEL
bonsancon_pyblaze-0.0.11.dist-info/top_level.txt
bonsancon_pyblaze-0.0.11.dist-info/RECORD
