Metadata-Version: 2.1
Name: bonsancon-pyblaze
Version: 0.0.11
Summary: Blaze API
Home-page: https://github.com/bonsancon/pyblaze
Author: Álvaro Ferreira Pires de Paiva
Author-email: alvarofepipa@gmail.com
License: UNKNOWN
Platform: UNKNOWN
Classifier: Programming Language :: Python :: 3
Classifier: License :: OSI Approved :: MIT License
Classifier: Operating System :: OS Independent
Requires-Dist: pydantic (>=1.9.1)
Requires-Dist: requests (>=2.28.0)
